{
  "concepts": 29959, 
  "conceptsWithoutStrings": 14411, 
  "facets": {
    "CompoundConcept": {
      "concepts": 990, 
      "prefLabels": {}, 
      "terms": 0
    }, 
    "GenreForm": {
      "altLabels": {
        "en": 18, 
        "la": 0, 
        "nb": 103, 
        "nn": 0
      }, 
      "concepts": 126, 
      "prefLabels": {
        "en": 31, 
        "la": 0, 
        "nb": 126, 
        "nn": 5
      }, 
      "terms": 283
    }, 
    "Place": {
      "altLabels": {
        "en": 143, 
        "la": 0, 
        "nb": 96, 
        "nn": 7
      }, 
      "concepts": 885, 
      "prefLabels": {
        "en": 837, 
        "la": 1, 
        "nb": 885, 
        "nn": 22
      }, 
      "terms": 1991
    }, 
    "Time": {
      "altLabels": {
        "en": 10, 
        "la": 0, 
        "nb": 21, 
        "nn": 1
      }, 
      "concepts": 23, 
      "prefLabels": {
        "en": 19, 
        "la": 0, 
        "nb": 23, 
        "nn": 1
      }, 
      "terms": 75
    }, 
    "Topic": {
      "altLabels": {
        "en": 1730, 
        "la": 24, 
        "nb": 4412, 
        "nn": 5379
      }, 
      "concepts": 13377, 
      "prefLabels": {
        "en": 5939, 
        "la": 354, 
        "nb": 13375, 
        "nn": 12062
      }, 
      "terms": 43275
    }, 
    "VirtualCompoundConcept": {
      "concepts": 14558, 
      "prefLabels": {}, 
      "terms": 0
    }
  }, 
  "features": {
    "broadMatch": 2544, 
    "closeMatch": 11200, 
    "definition": 458, 
    "editorialNote": 197, 
    "exactMatch": 3573, 
    "narrowMatch": 0, 
    "related": 1004, 
    "relatedMatch": 3555
  }, 
  "mappings": {
    "agrovoc": 1, 
    "ddc": 15709, 
    "tekord": 810
  }, 
  "terms": {
    "_sum": 92344, 
    "en": 24314, 
    "la": 379, 
    "nb": 34608, 
    "nn": 33043
  }, 
  "ts": 1516756476
}